auto_gate_opening/auto_gate_opening.v
module automatic_gate_controller (clk,reset,entry_sensor,exit_sensor,gate_open,gate_close);
    input  wire clk;
    input  wire reset;
    input  wire entry_sensor;
    input  wire exit_sensor;
    output reg  gate_open;
    output reg  gate_close;
  
  
    parameter IDLE    = 2'b00;
    parameter OPENING = 2'b01;
    parameter OPEN    = 2'b10;
    parameter CLOSING = 2'b11;
  
     reg [1:0] state,next_state;


     always @(posedge clk or posedge reset) begin
        if (reset)
            state <= IDLE;
        else
            state <= next_state;
    end

     always @(*) begin
        case (state)
            IDLE:     if (entry_sensor)
                          next_state = OPENING; 
                     else
                          next_state = IDLE;
                          
            OPENING:  next_state = OPEN;

            OPEN:     if (exit_sensor) 
                          next_state = CLOSING;
                      else
                          next_state = OPEN;
            CLOSING:  next_state = IDLE;
            default:  next_state = IDLE;
        endcase
    end

     always @(*) begin
        gate_open  = 0;
        gate_close = 0;

        case (state)
            OPENING:  gate_open  = 1;
            CLOSING:  gate_close = 1;
        endcase
    end

endmodule

auto_gate_opening/auto_gate_opening_tb.v
module automatic_gate_controller_tb();
    reg clk = 0, reset = 1;
    reg entry_sensor, exit_sensor;
    wire gate_open, gate_close;

    automatic_gate_controller dut (
        .clk(clk), .reset(reset),
        .entry_sensor(entry_sensor),
        .exit_sensor(exit_sensor),
        .gate_open(gate_open),
        .gate_close(gate_close)
    );

    always #5 clk = ~clk;

    initial begin
        $dumpfile("dump.vcd");
        $dumpvars(0,automatic_gate_controller_tb);
        $monitor("clk=%b reset=%b entry_sensor=%b exit_sensor=%b gate_open=%b gate_close=%b",clk,reset,entry_sensor,exit_sensor,gate_open,gate_close);
    reset = 1; 
        entry_sensor = 0; exit_sensor = 0; #10
        
     reset = 0;
         entry_sensor = 1; #10  entry_sensor = 0; #20    
         exit_sensor = 1;  #10  exit_sensor = 0; #20  

         $finish ;
    end
endmodule

auto_gate_opening/dump.vcd
$date
	Tue Jan 13 13:02:08 2026
$end
$version
	Icarus Verilog
$end
$timescale
	1s
$end
$scope module automatic_gate_controller_tb $end
$var wire 1 ! gate_open $end
$var wire 1 " gate_close $end
$var reg 1 # clk $end
$var reg 1 $ entry_sensor $end
$var reg 1 % exit_sensor $end
$var reg 1 & reset $end
$scope module dut $end
$var wire 1 # clk $end
$var wire 1 $ entry_sensor $end
$var wire 1 % exit_sensor $end
$var wire 1 & reset $end
$var parameter 2 ' CLOSING $end
$var parameter 2 ( IDLE $end
$var parameter 2 ) OPEN $end
$var parameter 2 * OPENING $end
$var reg 1 " gate_close $end
$var reg 1 ! gate_open $end
$var reg 2 + next_state [1:0] $end
$var reg 2 , state [1:0] $end
$upscope $end
$upscope $end
$enddefinitions $end
$comment Show the parameter values. $end
$dumpall
b1 *
b10 )
b0 (
b11 '
$end
#0
$dumpvars
b0 ,
b0 +
1&
0%
0$
0#
0"
0!
$end
#5
1#
#10
b1 +
0#
1$
0&
#15
1!
b10 +
b1 ,
1#
#20
0#
0$
#25
0!
b10 ,
1#
#30
0#
#35
1#
#40
b11 +
0#
1%
#45
1"
b0 +
b11 ,
1#
#50
0#
0%
#55
0"
b0 ,
1#
