lift_floor_indicator/lift_floor_indicator.v
module lift_floor_indicator(floor,seg);
input [2:0]floor;
output reg [6:0]seg;

always @(*) begin
   case(floor)

   3'b000: seg = 7'b1111110;
   3'b001: seg = 7'b0110000;
   3'b010: seg = 7'b1101101;
   3'b011: seg = 7'b1111001;
   3'b100: seg = 7'b0110011;
   3'b101: seg = 7'b1011011;
   3'b110: seg = 7'b1011111;
   3'b111: seg = 7'b1110000;
   default seg = 7'b0000000;
   endcase

end
endmodule

lift_floor_indicator/lift_floor_indicator_tb.v
module lift_floor_indicator_tb();
reg[2:0] floor;
wire[6:0] seg;

lift_floor_indicator uut(floor,seg);

initial begin

    $dumpfile("dump.vcd");
    $dumpvars(0,lift_floor_indicator_tb);
    $monitor("floor=%b seg=%b",floor,seg);

    floor = 3'b000; #10;
    floor = 3'b001; #10;
    floor = 3'b010; #10;
    floor = 3'b011; #10;
    floor = 3'b100; #10;
    floor = 3'b101; #10;
    floor = 3'b110; #10;
    floor = 3'b111; #10;

    $finish;
end
endmodule

lift_floor_indicator/dump.vcd
$date
	Tue Jan 13 12:16:43 2026
$end
$version
	Icarus Verilog
$end
$timescale
	1s
$end
$scope module lift_floor_indicator_tb $end
$var wire 7 ! seg [6:0] $end
$var reg 3 " floor [2:0] $end
$scope module uut $end
$var wire 3 # floor [2:0] $end
$var reg 7 $ seg [6:0] $end
$upscope $end
$upscope $end
$enddefinitions $end
$comment Show the parameter values. $end
$dumpall
$end
#0
$dumpvars
b1111110 $
b0 #
b0 "
b1111110 !
$end
#10
b110000 !
b110000 $
b1 "
b1 #
#20
b1101101 !
b1101101 $
b10 "
b10 #
#30
b1111001 !
b1111001 $
b11 "
b11 #
#40
b110011 !
b110011 $
b100 "
b100 #
#50
b1011011 !
b1011011 $
b101 "
b101 #
#60
b1011111 !
b1011111 $
b110 "
b110 #
#70
b1110000 !
b1110000 $
b111 "
b111 #
